mycotools/__init__.py
mycotools/acc2fa.py
mycotools/acc2fq.py
mycotools/acc2gbk.py
mycotools/acc2gff.py
mycotools/acc2locus.py
mycotools/add2gff.py
mycotools/annotationStats.py
mycotools/assemblyStats.py
mycotools/bioreform.py
mycotools/coords2fa.py
mycotools/crap.py
mycotools/db2files.py
mycotools/db2hgs.py
mycotools/db2microsyntree.py
mycotools/db2search.py
mycotools/extract_mtdb.py
mycotools/fa2clus.py
mycotools/fa2hmmer2fa.py
mycotools/fa2mass.py
mycotools/fa2tree.py
mycotools/fna2faa.py
mycotools/gff2seq.py
mycotools/gff2svg.py
mycotools/jgiDwnld.py
mycotools/manage_mtdb.py
mycotools/mtdb.py
mycotools/ncbiAcc2fa.py
mycotools/ncbiDwnld.py
mycotools/ncbi_dwnld_fallback.py
mycotools/ome2name.py
mycotools/predb2mtdb.py
mycotools/treetools.py
mycotools/update_mtdb.py
mycotools/lib/__init__.py
mycotools/lib/biotools.py
mycotools/lib/dbtools.py
mycotools/lib/kontools.py
mycotools/utils/__init__.py
mycotools/utils/curGFF3.py
mycotools/utils/extractHmmAcc.py
mycotools/utils/extractHmmsearch.py
mycotools/utils/gff2gff3.py
mycotools/utils/gtf2gff3.py
mycotools/utils/jgi2db.py
mycotools/utils/ncbi2db.py
mycotools/utils/og2mycodb.py
mycotools-1.0.0.dist-info/licenses/LICENSE
mycotools-1.0.0.dist-info/METADATA
mycotools-1.0.0.dist-info/WHEEL
mycotools-1.0.0.dist-info/entry_points.txt
mycotools-1.0.0.dist-info/top_level.txt
mycotools-1.0.0.dist-info/RECORD
