Metadata-Version: 2.4
Name: mycotools
Version: 1.0.0
Summary: Comparative genomics automation and standardization software
Author-email: Zachary Konkel <konkelzach@protonmail.com>
License: Copyright 2023 Zachary Konkel
Project-URL: Homepage, https://github.com/xonq/mycotools
Project-URL: Bug Tracker, https://github.com/xonq/mycotools/issues
Classifier: Programming Language :: Python :: 3
Classifier: License :: OSI Approved :: GNU Lesser General Public License v3 or later (LGPLv3+)
Classifier: Operating System :: POSIX :: Linux
Requires-Python: <4,>=3.0
License-File: LICENSE
Requires-Dist: biopython
Requires-Dist: pandas
Requires-Dist: requests
Requires-Dist: scipy
Requires-Dist: openpyxl
Requires-Dist: tqdm
Requires-Dist: cryptography
Requires-Dist: ete3
Requires-Dist: pyqt5
Dynamic: license-file
